dagnostics/__init__.py
dagnostics/api_client.py
dagnostics/main.py
dagnostics/analysis/__init__.py
dagnostics/analysis/analyzer.py
dagnostics/analysis/anomaly_detector.py
dagnostics/analysis/error_classifier.py
dagnostics/api/__init__.py
dagnostics/api/main.py
dagnostics/api/schemas.py
dagnostics/api/websocket_manager.py
dagnostics/api/routes/__init__.py
dagnostics/api/routes/analysis.py
dagnostics/api/routes/dashboard.py
dagnostics/api/routes/monitor.py
dagnostics/api/routes/training.py
dagnostics/cli/__init__.py
dagnostics/cli/commands.py
dagnostics/cli/feedback_commands.py
dagnostics/cli/main.py
dagnostics/cli/training_commands.py
dagnostics/cli/utils.py
dagnostics/clustering/__init__.py
dagnostics/clustering/base_clusterer.py
dagnostics/clustering/drain3_adapter.py
dagnostics/clustering/log_clusterer.py
dagnostics/core/__init__.py
dagnostics/core/airflow_client.py
dagnostics/core/config.py
dagnostics/core/database.py
dagnostics/core/exceptions.py
dagnostics/core/models.py
dagnostics/core/types.py
dagnostics/daemon/__init__.py
dagnostics/daemon/service.py
dagnostics/heuristics/__init__.py
dagnostics/heuristics/filter_factory.py
dagnostics/heuristics/filter_integration.py
dagnostics/heuristics/pattern_filter.py
dagnostics/heuristics/engines/__init__.py
dagnostics/heuristics/engines/custom_function_engine.py
dagnostics/heuristics/engines/regex_engine.py
dagnostics/heuristics/engines/substring_engine.py
dagnostics/heuristics/engines/threshold_engine.py
dagnostics/llm/__init__.py
dagnostics/llm/engine.py
dagnostics/llm/parser.py
dagnostics/llm/prompts.py
dagnostics/monitoring/__init__.py
dagnostics/monitoring/alert.py
dagnostics/monitoring/collector.py
dagnostics/monitoring/monitor.py
dagnostics/reporting/__init__.py
dagnostics/reporting/formatters.py
dagnostics/reporting/generator.py
dagnostics/reporting/templates.py
dagnostics/storage/__init__.py
dagnostics/storage/feedback_db.py
dagnostics/training/__init__.py
dagnostics/training/api_fine_tuner.py
dagnostics-0.7.6.dist-info/METADATA
dagnostics-0.7.6.dist-info/WHEEL
dagnostics-0.7.6.dist-info/entry_points.txt
dagnostics-0.7.6.dist-info/licenses/LICENSE
dagnostics-0.7.6.dist-info/RECORD
