Metadata-Version: 2.4
Name: dagnostics
Version: 0.7.6
Author-email: pesnik <hasanrakibul.masum@gmail.com>
License-File: LICENSE
Requires-Python: <4.0,>=3.10
Requires-Dist: apscheduler>=3.11.0
Requires-Dist: drain3>=0.9.11
Requires-Dist: dynaconf>=3.2.11
Requires-Dist: fastapi<0.116.0,>=0.115.6
Requires-Dist: google-generativeai>=0.8.5
Requires-Dist: psycopg2-binary>=2.9.10
Requires-Dist: pydantic[email]<3.0.0,>=2.10.5
Requires-Dist: python-dotenv<2.0.0,>=1.0.1
Requires-Dist: pyyaml<7.0.0,>=6.0.2
Requires-Dist: requests>=2.32.4
Requires-Dist: rich<14.0.0,>=13.9.4
Requires-Dist: sqlalchemy>=2.0.41
Requires-Dist: typer<0.16.0,>=0.15.1
Requires-Dist: uvicorn[standard]<0.35.0,>=0.34.0
Requires-Dist: websockets<14.0,>=12.0
Provides-Extra: all
Requires-Dist: accelerate>=0.24.0; extra == 'all'
Requires-Dist: anthropic>=0.59.0; extra == 'all'
Requires-Dist: bitsandbytes>=0.41.0; extra == 'all'
Requires-Dist: black>=24.10.0; extra == 'all'
Requires-Dist: datasets>=2.14.0; extra == 'all'
Requires-Dist: flake8>=7.1.1; extra == 'all'
Requires-Dist: google-generativeai>=0.8.5; extra == 'all'
Requires-Dist: invoke>=2.2.0; extra == 'all'
Requires-Dist: isort>=5.13.2; extra == 'all'
Requires-Dist: langchain-community<0.4.0,>=0.3.14; extra == 'all'
Requires-Dist: langchain-core<0.4.0,>=0.3.30; extra == 'all'
Requires-Dist: langchain<0.4.0,>=0.3.14; extra == 'all'
Requires-Dist: mypy>=1.14.1; extra == 'all'
Requires-Dist: openai>=1.97.1; extra == 'all'
Requires-Dist: peft>=0.6.0; extra == 'all'
Requires-Dist: pre-commit>=4.2.0; extra == 'all'
Requires-Dist: pylint-venv>=3.0.4; extra == 'all'
Requires-Dist: pytest-cov>=6.0.0; extra == 'all'
Requires-Dist: pytest>=8.3.4; extra == 'all'
Requires-Dist: torch>=2.0.0; extra == 'all'
Requires-Dist: transformers>=4.35.0; extra == 'all'
Requires-Dist: types-pyyaml>=6.0.12.20241230; extra == 'all'
Requires-Dist: types-requests>=2.32.4.20250611; extra == 'all'
Provides-Extra: dev
Requires-Dist: black>=24.10.0; extra == 'dev'
Requires-Dist: flake8>=7.1.1; extra == 'dev'
Requires-Dist: invoke>=2.2.0; extra == 'dev'
Requires-Dist: isort>=5.13.2; extra == 'dev'
Requires-Dist: mypy>=1.14.1; extra == 'dev'
Requires-Dist: pre-commit>=4.2.0; extra == 'dev'
Requires-Dist: pylint-venv>=3.0.4; extra == 'dev'
Requires-Dist: pytest-cov>=6.0.0; extra == 'dev'
Requires-Dist: pytest>=8.3.4; extra == 'dev'
Requires-Dist: types-pyyaml>=6.0.12.20241230; extra == 'dev'
Requires-Dist: types-requests>=2.32.4.20250611; extra == 'dev'
Provides-Extra: finetuning
Requires-Dist: accelerate>=0.24.0; extra == 'finetuning'
Requires-Dist: bitsandbytes>=0.41.0; extra == 'finetuning'
Requires-Dist: datasets>=2.14.0; extra == 'finetuning'
Requires-Dist: peft>=0.6.0; extra == 'finetuning'
Requires-Dist: torch>=2.0.0; extra == 'finetuning'
Requires-Dist: transformers>=4.35.0; extra == 'finetuning'
Provides-Extra: llm
Requires-Dist: anthropic>=0.59.0; extra == 'llm'
Requires-Dist: google-generativeai>=0.8.5; extra == 'llm'
Requires-Dist: langchain-community<0.4.0,>=0.3.14; extra == 'llm'
Requires-Dist: langchain-core<0.4.0,>=0.3.30; extra == 'llm'
Requires-Dist: langchain<0.4.0,>=0.3.14; extra == 'llm'
Requires-Dist: openai>=1.97.1; extra == 'llm'
Provides-Extra: web
Requires-Dist: drain3>=0.9.11; extra == 'web'
Requires-Dist: dynaconf>=3.2.11; extra == 'web'
Requires-Dist: fastapi<0.116.0,>=0.115.6; extra == 'web'
Requires-Dist: pydantic[email]<3.0.0,>=2.10.5; extra == 'web'
Requires-Dist: python-dotenv<2.0.0,>=1.0.1; extra == 'web'
Requires-Dist: pyyaml<7.0.0,>=6.0.2; extra == 'web'
Requires-Dist: requests>=2.32.4; extra == 'web'
Requires-Dist: rich<14.0.0,>=13.9.4; extra == 'web'
Requires-Dist: sqlalchemy>=2.0.41; extra == 'web'
Requires-Dist: typer<0.16.0,>=0.15.1; extra == 'web'
Requires-Dist: uvicorn[standard]<0.35.0,>=0.34.0; extra == 'web'
Requires-Dist: websockets<14.0,>=12.0; extra == 'web'
